{
    "transforms": [
        6.362074851989746,
        2.8725087642669679,
        0.0,
        1.0,
        1.0,
        1.0,
        5.149239540100098,
        -1.021336317062378,
        0.0,
        5.0,
        0.5,
        2.0,
        -8.745196342468262,
        2.340564250946045,
        0.0,
        1.0,
        1.0,
        1.0,
        1.2805376052856446,
        -2.1916184425354006,
        0.0,
        3.6323423385620119,
        -2.299999952316284,
        3.6323423385620119,
        1.2805376052856446,
        -2.1916184425354006,
        0.0,
        -5.0,
        1.0,
        1.0,
        -1.4256157875061036,
        -2.681008815765381,
        0.0,
        10.0,
        0.20000000298023225,
        2.0,
        -7.872803688049316,
        -0.8936704993247986,
        0.0,
        5.0,
        0.5,
        2.0
    ],
    "ids": [
        "to_save_bila",
        "to_save_plan_inclinat",
        "to_save_bila",
        "Circle",
        "to_save_resort",
        "to_save_cub",
        "to_save_plan_inclinat"
    ],
    "rotations": [
        {
            "x": -0.7071068286895752,
            "y": 0.0,
            "z": 0.0,
            "w": 0.7071067094802856
        },
        {
            "x": 0.0,
            "y": 0.0,
            "z": 0.3826834261417389,
            "w": 0.9238795638084412
        },
        {
            "x": -0.7071068286895752,
            "y": 0.0,
            "z": 0.0,
            "w": 0.7071067094802856
        },
        {
            "x": 0.0,
            "y": 0.0,
            "z": 0.7071068286895752,
            "w": 0.7071068286895752
        },
        {
            "x": 0.0,
            "y": 0.0,
            "z": 0.0,
            "w": 1.0
        },
        {
            "x": 0.0,
            "y": 0.0,
            "z": 0.0,
            "w": 1.0
        },
        {
            "x": 0.0,
            "y": 0.0,
            "z": -0.3826834261417389,
            "w": 0.9238795638084412
        }
    ],
    "tag": []
}